gatewizard/__init__.py
gatewizard/main.py
gatewizard/core/__init__.py
gatewizard/core/builder.py
gatewizard/core/file_manager.py
gatewizard/core/job_monitor.py
gatewizard/core/preparation.py
gatewizard/gui/__init__.py
gatewizard/gui/app.py
gatewizard/gui/constants.py
gatewizard/gui/base/__init__.py
gatewizard/gui/base/callback_manager.py
gatewizard/gui/frames/__init__.py
gatewizard/gui/frames/analysis.py
gatewizard/gui/frames/builder_frame.py
gatewizard/gui/frames/equilibration.py
gatewizard/gui/frames/preparation_frame.py
gatewizard/gui/frames/visualize.py
gatewizard/gui/widgets/__init__.py
gatewizard/gui/widgets/leaflet_frame.py
gatewizard/gui/widgets/progress_tracker.py
gatewizard/gui/widgets/propka_workflow_helper.py
gatewizard/gui/widgets/searchable_combobox.py
gatewizard/gui/widgets/stage_tabs.py
gatewizard/tools/__init__.py
gatewizard/tools/equilibration.py
gatewizard/tools/force_fields.py
gatewizard/tools/molecular_viewer.py
gatewizard/tools/validators.py
gatewizard/utils/__init__.py
gatewizard/utils/bilayer_utils.py
gatewizard/utils/config.py
gatewizard/utils/helpers.py
gatewizard/utils/logger.py
gatewizard/utils/namd_analysis.py
gatewizard/utils/optional_deps.py
gatewizard/utils/protein_capping.py
gatewizard-1.0.17.dist-info/licenses/LICENSE
tests/__init__.py
tests/test_analysis.py
tests/test_builder.py
tests/test_equilibration.py
tests/test_preparation.py
tests/analysis_examples/analysis_example_01.py
tests/analysis_examples/analysis_example_02.py
tests/analysis_examples/analysis_example_03.py
tests/analysis_examples/analysis_example_04.py
tests/analysis_examples/analysis_example_05.py
tests/analysis_examples/analysis_example_06.py
tests/analysis_examples/analysis_example_07.py
tests/analysis_examples/analysis_example_08.py
tests/analysis_examples/analysis_example_09.py
tests/analysis_examples/analysis_example_10.py
tests/builder_examples/builder_example_01.py
tests/builder_examples/builder_example_02.py
tests/builder_examples/builder_example_03.py
tests/builder_examples/builder_example_04.py
gatewizard-1.0.17.dist-info/METADATA
gatewizard-1.0.17.dist-info/WHEEL
gatewizard-1.0.17.dist-info/entry_points.txt
gatewizard-1.0.17.dist-info/top_level.txt
gatewizard-1.0.17.dist-info/RECORD
