Metadata-Version: 2.4
Name: gatewizard
Version: 1.0.17
Summary: A tool for membrane protein preparation and molecular dynamics analysis
Author-email: Constanza González <constanza.gonzalez.villagra@gmail.com>, Mauricio Bedoya <mbedoya@ucm.cl>
License: MIT License
Classifier: Development Status :: 4 - Beta
Classifier: Intended Audience :: Science/Research
Classifier: License :: OSI Approved :: MIT License
Classifier: Operating System :: OS Independent
Classifier: Programming Language :: Python :: 3
Classifier: Programming Language :: Python :: 3.8
Classifier: Programming Language :: Python :: 3.9
Classifier: Programming Language :: Python :: 3.10
Classifier: Programming Language :: Python :: 3.11
Classifier: Programming Language :: Python :: 3.12
Classifier: Topic :: Scientific/Engineering :: Bio-Informatics
Classifier: Topic :: Scientific/Engineering :: Chemistry
Requires-Python: >=3.8
License-File: LICENSE
Requires-Dist: customtkinter>=5.0.0
Requires-Dist: numpy>=1.21.0
Requires-Dist: matplotlib>=3.5.0
Requires-Dist: requests>=2.25.0
Requires-Dist: MDAnalysis>=2.0.0
Requires-Dist: propka>=3.2.0
Provides-Extra: analysis
Requires-Dist: MDAnalysis>=2.0.0; extra == "analysis"
Provides-Extra: all
Requires-Dist: MDAnalysis>=2.0.0; extra == "all"
Dynamic: license-file
